budgetize/__init__.py
budgetize/__main__.py
budgetize/budget.py
budgetize/console.py
budgetize/consts.py
budgetize/currency_manager.py
budgetize/db/database.py
budgetize/db/orm/_base.py
budgetize/db/orm/account.py
budgetize/db/orm/transactions.py
budgetize/exceptions.py
budgetize/exchange_rate.py
budgetize/settings_manager.py
budgetize/translations/es/es.po
budgetize/translations/es/LC_MESSAGES/budgetize.mo
budgetize/translations/TRANSLATION_TEMPLATE.po
budgetize/tui/__init__.py
budgetize/tui/modals/categories_modal.py
budgetize/tui/modals/confirm_modal.py
budgetize/tui/modals/css/confirm_quit.tcss
budgetize/tui/modals/css/error_modal.tcss
budgetize/tui/modals/css/file_selector_modal.tcss
budgetize/tui/modals/css/input_modal.tcss
budgetize/tui/modals/css/message_modal.tcss
budgetize/tui/modals/css/transaction_details.tcss
budgetize/tui/modals/error_modal.py
budgetize/tui/modals/file_selector_modal.py
budgetize/tui/modals/input_modal.py
budgetize/tui/modals/message_modal.py
budgetize/tui/modals/transaction_details.py
budgetize/tui/screens/add_transaction.py
budgetize/tui/screens/create_account.py
budgetize/tui/screens/create_budget.py
budgetize/tui/screens/css/create_account.tcss
budgetize/tui/screens/css/create_budget.tcss
budgetize/tui/screens/css/initial_config.tcss
budgetize/tui/screens/css/main_menu.tcss
budgetize/tui/screens/css/settings.tcss
budgetize/tui/screens/css/transfer.tcss
budgetize/tui/screens/initial_config.py
budgetize/tui/screens/main_menu.py
budgetize/tui/screens/manage_accounts.py
budgetize/tui/screens/settings.py
budgetize/tui/screens/transfer.py
budgetize/tui/tui_app.py
budgetize/utils.py
budgetize-0.2.1.dist-info/entry_points.txt
budgetize-0.2.1.dist-info/LICENSE
budgetize-0.2.1.dist-info/METADATA
budgetize-0.2.1.dist-info/WHEEL
budgetize-0.2.1.dist-info/RECORD
