Metadata-Version: 2.1
Name: budgetize
Version: 0.2.1
Summary: A Terminal User Interface (TUI) to create budgets, track your incomes/expenses and manage your finances.
Home-page: https://github.com/fer-hnndz/budgetize
License: GPL-3.0-only
Keywords: budget,finance,expense,tracker
Author: fer-hnndz
Author-email: jfernandohernandez28@gmail.com
Requires-Python: >=3.9,<4.0
Classifier: Development Status :: 3 - Alpha
Classifier: Intended Audience :: End Users/Desktop
Classifier: License :: OSI Approved :: GNU General Public License v3 (GPLv3)
Classifier: Operating System :: OS Independent
Classifier: Programming Language :: Python :: 3
Classifier: Programming Language :: Python :: 3.9
Classifier: Programming Language :: Python :: 3.10
Classifier: Programming Language :: Python :: 3.11
Classifier: Programming Language :: Python :: 3.12
Requires-Dist: Babel (>=2.14.0,<3.0.0)
Requires-Dist: SQLAlchemy (>=2.0.29,<3.0.0)
Requires-Dist: arrow (>=1.3.0,<2.0.0)
Requires-Dist: asyncio (>=3.4.3,<4.0.0)
Requires-Dist: beautifulsoup4 (>=4.12.3,<5.0.0)
Requires-Dist: httpx
Requires-Dist: pyperclip (>=1.8.2,<2.0.0)
Requires-Dist: setuptools (>=72.1.0,<73.0.0)
Requires-Dist: textual
Project-URL: Repository, https://github.com/fer-hnndz/budgetize
